sigmap/__init__.py
sigmap/polygeohasher/__init__.py
sigmap/polygeohasher/adaptative_geohash_coverage.py
sigmap/polygeohasher/logger.py
sigmap/polygeohasher/plot_geohash_coverage.py
sigmap/polygeohasher/utils/__init__.py
sigmap/polygeohasher/utils/algorithms.py
sigmap/polygeohasher/utils/gadm_download.py
sigmap/polygeohasher/utils/geohash.py
sigmap/polygeohasher/utils/polygons.py
sigmap_pytools-0.0.1.dist-info/METADATA
sigmap_pytools-0.0.1.dist-info/WHEEL
sigmap_pytools-0.0.1.dist-info/RECORD
